{"is_source_file": true, "format": "JavaScript (React JSX)", "description": "This file is the main application component for a React-based frontend project. It sets up routing for both public and protected pages, wraps the application with context providers for authentication and currency, and defines the overall navigation structure.", "external_files": ["./auth/AuthContext", "./currency/CurrencyContext", "./routes/ProtectedRoute", "./pages/Landing", "./pages/AuthCallback", "./pages/Dashboard", "./pages/Transactions", "./pages/Insights", "./pages/Alerts", "./pages/Settings", "./App.css", "./styles/theme.css"], "external_methods": ["React", "BrowserRouter", "Routes", "Route", "Navigate", "AuthProvider", "CurrencyProvider", "ProtectedRoute"], "published": ["App"], "classes": [{"name": "App", "description": "Main React component that sets up routing and context providers for the frontend application."}], "methods": [{"name": "App()", "description": "Functional component acting as the root component of the frontend app, setting up routes and context providers.", "scope": "", "scopeKind": ""}], "calls": ["React", "BrowserRouter", "Routes", "Route", "Navigate", "AuthProvider", "CurrencyProvider", "ProtectedRoute", "LandingPage", "AuthCallbackPage", "DashboardPage", "TransactionsPage", "InsightsPage", "AlertsPage", "SettingsPage"], "search-terms": ["React routing", "ProtectedRoute", "AuthContext", "CurrencyContext", "main app component", "frontend routing structure"], "state": 2, "file_id": 5, "knowledge_revision": 97, "git_revision": "f7fcc5d989b8f1395dafa4bd106d15ddaef0c91b", "revision_history": [{"22": "60eedcf46c0fad830c8780a4d4d940c1f10eb67b"}, {"39": "33dfbb9a73ff5d92eed9210278685e2a31eb05cd"}, {"88": "d5376a5a591f58c9b338c764a3fa3c47c7f78c5d"}, {"97": "f7fcc5d989b8f1395dafa4bd106d15ddaef0c91b"}], "ctags": [{"_type": "tag", "name": "App", "path": "/home/kavia/workspace/code-generation/spendsense-analytics-dashboard-40846-40855/spendsense_frontend/src/App.js", "pattern": "/^function App() {$/", "language": "JavaScript", "kind": "function", "signature": "()"}], "hash": "eb119208ff5868c85972b38bf7b2eab9", "format-version": 4, "code-base-name": "spendsense_frontend", "filename": "spendsense_frontend/src/App.js"}